python_learning_tracker/__init__.py
python_learning_tracker/api.py
python_learning_tracker/cli.py
python_learning_tracker/learning_python.py
python_learning_tracker/web.py
python_learning_tracker/data/abbreviations.csv
python_learning_tracker/data/actual.csv
python_learning_tracker/data/motivation.txt
python_learning_tracker/data/planned.csv
python_learning_tracker/templates/404.html
python_learning_tracker/templates/base.html
python_learning_tracker/templates/index.html
python_learning_tracker/templates/report.html
python_learning_tracker/templates/search.html
python_learning_tracker/templates/topic_detail.html
python_learning_tracker/templates/topics.html
python_learning_tracker-1.2.0.dist-info/licenses/LICENSE.txt
python_learning_tracker-1.2.0.dist-info/METADATA
python_learning_tracker-1.2.0.dist-info/WHEEL
python_learning_tracker-1.2.0.dist-info/entry_points.txt
python_learning_tracker-1.2.0.dist-info/top_level.txt
python_learning_tracker-1.2.0.dist-info/RECORD
