Metadata-Version: 2.4
Name: python_learning_tracker
Version: 1.2.0
Summary: Flask-додаток для аналізу прогресу навчання Python
Author: 
Author-email: 
License: MIT License
Requires-Python: >=3.10
License-File: LICENSE.txt
Requires-Dist: flask
Requires-Dist: jinja2
Requires-Dist: flask-restful
Requires-Dist: flasgger
Provides-Extra: dev
Requires-Dist: pytest; extra == "dev"
Requires-Dist: pytest-cov; extra == "dev"
Requires-Dist: ruff; extra == "dev"
Dynamic: license-file
